Metadata-Version: 2.4
Name: elastic-apm
Version: 6.24.0
Summary: The official Python module for Elastic APM
Home-page: https://github.com/elastic/apm-agent-python
Author: Elastic, Inc
License: BSD
Project-URL: Documentation, https://www.elastic.co/guide/en/apm/agent/python/current/index.html
Project-URL: Release notes, https://www.elastic.co/guide/en/apm/agent/python/current/release-notes.html
Project-URL: Source, https://github.com/elastic/apm-agent-python
Project-URL: Tracker, https://github.com/elastic/apm-agent-python/issues
Classifier: Intended Audience :: Developers
Classifier: Intended Audience :: System Administrators
Classifier: Operating System :: OS Independent
Classifier: Topic :: Software Development
Classifier: Programming Language :: Python
Classifier: Programming Language :: Python :: 3.6
Classifier: Programming Language :: Python :: 3.7
Classifier: Programming Language :: Python :: 3.8
Classifier: Programming Language :: Python :: 3.9
Classifier: Programming Language :: Python :: 3.10
Classifier: Programming Language :: Python :: 3.11
Classifier: Programming Language :: Python :: 3.12
Classifier: Programming Language :: Python :: 3.13
Classifier: Programming Language :: Python :: Implementation :: CPython
Classifier: Programming Language :: Python :: Implementation :: PyPy
Classifier: License :: OSI Approved :: BSD License
Requires-Python: <4,>=3.6
License-File: LICENSE
Requires-Dist: urllib3!=2.0.0,<3.0.0
Requires-Dist: certifi
Requires-Dist: wrapt!=1.15.0,>=1.14.1
Requires-Dist: ecs_logging
Provides-Extra: flask
Requires-Dist: blinker; extra == "flask"
Provides-Extra: aiohttp
Requires-Dist: aiohttp; extra == "aiohttp"
Provides-Extra: tornado
Requires-Dist: tornado; extra == "tornado"
Provides-Extra: starlette
Requires-Dist: starlette; extra == "starlette"
Provides-Extra: opentracing
Requires-Dist: opentracing>=2.0.0; extra == "opentracing"
Provides-Extra: sanic
Requires-Dist: sanic; extra == "sanic"
Provides-Extra: opentelemetry
Requires-Dist: opentelemetry-api; extra == "opentelemetry"
Requires-Dist: opentelemetry-sdk; extra == "opentelemetry"
Dynamic: license-file
